flood_adapt/__init__.py
flood_adapt/flood_adapt.py
flood_adapt/adapter/__init__.py
flood_adapt/adapter/fiat_adapter.py
flood_adapt/adapter/sfincs_adapter.py
flood_adapt/adapter/sfincs_offshore.py
flood_adapt/adapter/interface/__init__.py
flood_adapt/adapter/interface/hazard_adapter.py
flood_adapt/adapter/interface/impact_adapter.py
flood_adapt/adapter/interface/model_adapter.py
flood_adapt/adapter/interface/offshore.py
flood_adapt/config/__init__.py
flood_adapt/config/config.py
flood_adapt/config/fiat.py
flood_adapt/config/gui.py
flood_adapt/config/hazard.py
flood_adapt/config/impacts.py
flood_adapt/config/sfincs.py
flood_adapt/config/site.py
flood_adapt/database_builder/__init__.py
flood_adapt/database_builder/database_builder.py
flood_adapt/database_builder/metrics_utils.py
flood_adapt/database_builder/templates/default_units/imperial.toml
flood_adapt/database_builder/templates/default_units/metric.toml
flood_adapt/database_builder/templates/green_infra_table/green_infra_lookup_table.csv
flood_adapt/database_builder/templates/icons/black_down_48x48.png
flood_adapt/database_builder/templates/icons/black_left_48x48.png
flood_adapt/database_builder/templates/icons/black_right_48x48.png
flood_adapt/database_builder/templates/icons/black_up_48x48.png
flood_adapt/database_builder/templates/icons/icons8-triangle-arrow-16_white_down.png
flood_adapt/database_builder/templates/icons/icons8-triangle-arrow-16_white_left.png
flood_adapt/database_builder/templates/icons/icons8-triangle-arrow-16_white_right.png
flood_adapt/database_builder/templates/icons/icons8-triangle-arrow-16_white_up.png
flood_adapt/database_builder/templates/icons/icons8-triangle-arrow-24_black_down.png
flood_adapt/database_builder/templates/icons/icons8-triangle-arrow-24_black_left.png
flood_adapt/database_builder/templates/icons/icons8-triangle-arrow-24_black_right.png
flood_adapt/database_builder/templates/icons/icons8-triangle-arrow-24_black_up.png
flood_adapt-2.0.0.dist-info/LICENSE
flood_adapt-2.0.0.dist-info/METADATA
flood_adapt-2.0.0.dist-info/WHEEL
flood_adapt-2.0.0.dist-info/top_level.txt
flood_adapt-2.0.0.dist-info/RECORD
