Metadata-Version: 2.2
Name: flood-adapt
Version: 2.0.0
Summary: A software package support system which can be used to assess the benefits and costs of flood resilience measures
Author-email: Gundula Winter <Gundula.Winter@deltares.nl>, Panos Athanasiou <Panos.Athanasiou@deltares.nl>, Frederique de Groen <Frederique.deGroen@deltares.nl>, Tim de Wilde <Tim.deWilde@deltares.nl>, Julian Hofer <Julian.Hofer@deltares.nl>, Daley Adrichem <Daley.Adrichem@deltares.nl>, Luuk Blom <Luuk.Blom@deltares.nl>
License: ====================================================
Project-URL: Source, https://github.com/Deltares-research/FloodAdapt
Classifier: Intended Audience :: Science/Research
Classifier: License :: CC0 1.0 Universal (CC0 1.0) Public Domain Dedication
Classifier: Topic :: Scientific/Engineering :: Hydrology
Requires-Python: <3.13,>=3.10
License-File: LICENSE
Requires-Dist: cht-cyclones<2.0,>=1.0.3
Requires-Dist: cht-meteo<1.0,>=0.3.1
Requires-Dist: cht-observations<1.0,>=0.2.1
Requires-Dist: cht-tide<1.0,>=0.1.1
Requires-Dist: fiat-toolbox<0.2.0,>=0.1.22
Requires-Dist: fiona<2.0,>=1.0
Requires-Dist: geojson<4.0,>=3.0
Requires-Dist: geopandas<2.0,>=1.0
Requires-Dist: hydromt-fiat<1.0,>=0.5.9
Requires-Dist: hydromt-sfincs[quadtree]<2.0,>=1.2.2
Requires-Dist: numpy<2.0,>=1.0
Requires-Dist: numpy-financial<2.0,>=1.0
Requires-Dist: pandas<3.0,>=2.0
Requires-Dist: plotly<6.3,>=6.0
Requires-Dist: pydantic<3.0,>=2.0
Requires-Dist: pydantic-settings<3.0,>=2.0
Requires-Dist: pyogrio<1.0
Requires-Dist: tomli<3.0,>=2.0
Requires-Dist: tomli-w<2.0,>=1.0
Requires-Dist: typing_extensions
Provides-Extra: dev
Requires-Dist: pytest<9.0,>=8.0; extra == "dev"
Requires-Dist: pytest-cov<7.0,>=6.0; extra == "dev"
Requires-Dist: pre-commit==3.8.0; extra == "dev"
Requires-Dist: ruff==0.5.5; extra == "dev"
Requires-Dist: typos==1.23.6; extra == "dev"
Provides-Extra: build
Requires-Dist: build<2.0,>=1.2; extra == "build"
Requires-Dist: twine<7.0,>=6.0; extra == "build"
Requires-Dist: pyinstaller==6.13.0; extra == "build"
Requires-Dist: pefile<2024.8.26; extra == "build"
Provides-Extra: docs
Requires-Dist: jupyter<2.0,>=1.0; extra == "docs"
Requires-Dist: jupyter-cache<2.0,>=1.0; extra == "docs"
Requires-Dist: nbstripout<0.9,>=0.8.0; extra == "docs"
Requires-Dist: matplotlib<4.0,>=3.0; extra == "docs"
Requires-Dist: quartodoc<1.0,>=0.9.0; extra == "docs"
Requires-Dist: sphinx<9.0,>=8.0; extra == "docs"
Requires-Dist: sphinx-rtd-theme<4.0,>=3.0; extra == "docs"
Requires-Dist: regex<2025.0,>=2024.11; extra == "docs"
Requires-Dist: minio<8,>=7.2.15; extra == "docs"
Requires-Dist: python-dotenv<2.0,>=1.0; extra == "docs"
Requires-Dist: folium<1.0,>=0.19.0; extra == "docs"
Requires-Dist: mapclassify<3.0,>=2.8.0; extra == "docs"
Requires-Dist: contextily; extra == "docs"
